{  
    "data":{  
       "branch_id":"60",
       "building_id":2,
       "floor_id":5,
       "station_id":17,
       "inventory_id":null,
       "model_id":7688,
       "device_type_id":1,
       "code":"ABR-000014",
       "serial_no":"132456",
       "brand_id":3237,
       "parent_inventory_id":null,
       "name":null,
       "responsible_user_id":4968,
       "risk_level_type_id":2,
       "device_class_id":22,
       "guarantee_period":4,
       "created_by":30401,
       "updated_by":null,
       "device_feature_type_id":null,
       "document_type":null,
       "guarantee_expiry_at":"25.03.2018",
       "produce_at":"25.11.2017",
       "device_order_info_type_id":0,
       "device_sub_type_id":null,
       "legal_personality_id":2,
       "device_status_type_id":2,
       "note":null,
       "company_id":null,
       "department_id":2,
       "medical_service_code":"26",
       "device_location_id":231,
       "image":null,
       "image_path":"inventory\\image\\7179c29f-4084-4260-b329-f58910ea0a57.jpg",
       "leasing_company_id":null,
       "leasing_started_at":"01.01.0001",
       "leasing_finished_at":"01.01.0001",
       "purchase_info_invoice_date":"01.01.0001",
       "purchase_info_invoice_no":null,
       "purchase_info_company_id":null,
       "purchase_info_price":null,
       "malfunction_infos":[  
 
       ],
       "deviceMalfunctionInfo":[  
 
       ],
       "inventory":{  
          "name":null,
          "model_id":7688,
          "brand_id":3237,
          "device_type_id":1,
          "code":"ABR-000014",
          "serial_no":"132456",
          "last_location_id":0,
          "parent_inventory_id":null,
          "responsible_user_id":4968,
          "risk_level_type_id":2,
          "device_class_id":22,
          "guarantee_period":4,
          "guarantee_expiry_at":"2018-03-25T00:00:00",
          "produce_at":"2017-11-25T00:00:00",
          "device_order_info_type_id":0,
          "device_sub_type_id":null,
          "legal_personality_id":2,
          "device_status_type_id":2,
          "note":null,
          "company_id":null,
          "department_id":2,
          "medical_service_code":"26",
          "created_by":30401,
          "updated_by":null,
          "device_feature_type_id":null,
          "image":null,
          "image_path":"inventory\\image\\7179c29f-4084-4260-b329-f58910ea0a57.jpg",
          "has_insurance":false,
          "id":0,
          "created_at":"2017-12-29T13:44:55.2875642+03:00",
          "updated_at":"2017-12-29T13:44:55.2875642+03:00",
          "deleted_at":null
       },
       "inventoryLocation":{  
          "inventory_id":null,
          "branch_id":"60",
          "building_id":2,
          "floor_id":5,
          "station_id":17,
          "device_location_id":231,
          "created_by":30401,
          "id":0,
          "created_at":"2017-12-29T13:44:55.2985716+03:00",
          "updated_at":"2017-12-29T13:44:55.2985716+03:00",
          "deleted_at":null
       }
    },
    "errors":null,
    "success":true,
    "extras":null
 }